odrive/__init__.py
odrive/api_client.py
odrive/config.py
odrive/crypto.py
odrive/database.py
odrive/dfu.py
odrive/enums.py
odrive/firmware.py
odrive/hw_version.py
odrive/legacy.py
odrive/legacy_config.py
odrive/release_api.py
odrive/rich_text.py
odrive/shell.py
odrive/utils.py
odrive/version.py
odrive/data/brakeRs.json
odrive/data/drvs.json
odrive/data/encoders.json
odrive/data/motors.json
odrive/data/odrive-s1-x4.json
odrive/data/odrive-v4.4.json
odrive/data/schema-brakeR.json
odrive/data/schema-drv.json
odrive/data/schema-encoders.json
odrive/data/schema-motors.json
odrive/data/schema-odrive.json
odrive/data/schema.json
odrive/dfuse/DfuDevice.py
odrive/dfuse/__init__.py
odrive/pyfibre/fibre/__init__.py
odrive/pyfibre/fibre/libfibre-linux-aarch64.so
odrive/pyfibre/fibre/libfibre-linux-amd64.so
odrive/pyfibre/fibre/libfibre-linux-armhf.so
odrive/pyfibre/fibre/libfibre-macos-arm.dylib
odrive/pyfibre/fibre/libfibre-macos-x86.dylib
odrive/pyfibre/fibre/libfibre-windows-amd64.dll
odrive/pyfibre/fibre/libfibre.py
odrive/pyfibre/fibre/libwinpthread-1.dll
odrive/pyfibre/fibre/shell.py
odrive/pyfibre/fibre/utils.py
odrive-0.6.7.data/scripts/odrive_demo.py
odrive-0.6.7.data/scripts/odrivetool
odrive-0.6.7.data/scripts/odrivetool.bat
odrive-0.6.7.dist-info/METADATA
odrive-0.6.7.dist-info/WHEEL
odrive-0.6.7.dist-info/top_level.txt
odrive-0.6.7.dist-info/RECORD
