Metadata-Version: 2.1
Name: odrive
Version: 0.6.7
Summary: Control utilities for the ODrive high performance motor controller
Home-page: https://odriverobotics.com/
Author: ODrive Robotics Inc
Author-email: info@odriverobotics.com
License: MIT
Keywords: odrive,motor,motor control,servo
Platform: UNKNOWN
Requires-Dist: PyUSB
Requires-Dist: aiohttp
Requires-Dist: appdirs
Requires-Dist: ipython
Requires-Dist: pyelftools
Requires-Dist: setuptools
Requires-Dist: pywin32 (>=222) ; platform_system == "Windows"
Provides-Extra: liveplotter
Requires-Dist: matplotlib ; extra == 'liveplotter'
